LICENSE.txt
MANIFEST.in
README
setup.py
scrimer/__init__.py
scrimer/primer3_connector.py
scrimer/pyvcf_filters.py
scrimer.egg-info/PKG-INFO
scrimer.egg-info/SOURCES.txt
scrimer.egg-info/dependency_links.txt
scrimer.egg-info/entry_points.txt
scrimer.egg-info/requires.txt
scrimer.egg-info/top_level.txt
scripts/5prime_stats.py
scripts/cigar_to_sim4db_scr.py
scripts/design_primers.py
scripts/extract_primers.py
scripts/fasta_fragments.py
scripts/fastq_kill_lines.py
scripts/find_redundant_sequences.py
scripts/liftover.py
scripts/scaffold.py
scripts/seq_filter_by_id.py