Metadata-Version: 1.0
Name: scrimer
Version: 1.0
Summary: Primer designing pipeline
Home-page: https://github.com/libor-m/scrimer
Author: Libor Morkovsky
Author-email: morkovsk@natur.cuni.cz
License:                     GNU AFFERO GENERAL PUBLIC LICENSE
